setup.cfg
setup.py
datando/__init__.py
datando/djd.py
datando/gregorian.py
datando/jd.py
datando/julian.py
datando/kernel.py
datando/mjd.py
datando/parser.py
datando/rjd.py
datando/tjd.py
datando.egg-info/PKG-INFO
datando.egg-info/SOURCES.txt
datando.egg-info/dependency_links.txt
datando.egg-info/top_level.txt